treediskanalyzer/__init__.py
treediskanalyzer/analyzer.py
treediskanalyzer/cli.py
treediskanalyzer/config.py
treediskanalyzer/main.py
treediskanalyzer/analysis/__init__.py
treediskanalyzer/analysis/chain_analysis_tools.py
treediskanalyzer/analysis/chain_neighbourhood.py
treediskanalyzer/analysis/chain_system_manager.py
treediskanalyzer/analysis/chains_bag.py
treediskanalyzer/analysis/connect_chains.py
treediskanalyzer/analysis/connect_parameters.py
treediskanalyzer/analysis/interpolation_nodes.py
treediskanalyzer/detection/__init__.py
treediskanalyzer/detection/canny_devernay_edge_detector.py
treediskanalyzer/detection/filter_edges.py
treediskanalyzer/externals/devernay_1.0/devernay.out
treediskanalyzer/geometry/__init__.py
treediskanalyzer/geometry/angular_set.py
treediskanalyzer/geometry/chain.py
treediskanalyzer/geometry/curve.py
treediskanalyzer/geometry/geometry_utils.py
treediskanalyzer/geometry/node.py
treediskanalyzer/geometry/ray.py
treediskanalyzer/geometry/ring.py
treediskanalyzer/geometry/virtual_band_generator.py
treediskanalyzer/processing/__init__.py
treediskanalyzer/processing/chain_context.py
treediskanalyzer/processing/postprocessing.py
treediskanalyzer/processing/preprocessing.py
treediskanalyzer/processing/sampling.py
treediskanalyzer/utils/__init__.py
treediskanalyzer/utils/file_utils.py
treediskanalyzer/utils/results_handler.py
treediskanalyzer/visualization/__init__.py
treediskanalyzer/visualization/color.py
treediskanalyzer/visualization/drawing.py
tree_disk_analyzer-0.4.1.dist-info/METADATA
tree_disk_analyzer-0.4.1.dist-info/WHEEL
tree_disk_analyzer-0.4.1.dist-info/entry_points.txt
tree_disk_analyzer-0.4.1.dist-info/top_level.txt
tree_disk_analyzer-0.4.1.dist-info/RECORD
