Metadata-Version: 2.1
Name: tree-disk-analyzer
Version: 0.4.1
Summary: A package for tree ring detection in images
Home-page: https://github.com/tuke307/tree-disk-analyzer
Author: Tony Meissner
Author-email: tonymeissner70@gmail.com
Requires-Python: >=3.7
Requires-Dist: numpy==2.1.2
Requires-Dist: matplotlib==3.9.2
Requires-Dist: opencv-python==4.10.0.84
Requires-Dist: opencv-contrib-python-headless==4.10.0.84
Requires-Dist: pandas==2.2.3
Requires-Dist: scikit-learn==1.5.2
Requires-Dist: natsort==8.4.0
Requires-Dist: glob2==0.7
Requires-Dist: shapely==2.0.6
Requires-Dist: imageio==2.36.0
Requires-Dist: Pillow==11.0.0
Requires-Dist: torch==2.5.0
Requires-Dist: torchvision==0.20.0
